{"type":"FeatureCollection","features":[{"type":"Feature","properties":{"stop_id":"2225","stop_code":"2225","stop_name":"Safeway Camino Tassajara","location_type":0,"parent_station":"","agency_key":"county-connection","agency_name":"County Connection","routes":[{"route_id":"41","route_short_name":"ALCR","route_long_name":"Alamo Creek Shuttle","route_color":"46A076","route_text_color":"ffffff"}]},"geometry":{"type":"Point","coordinates":[-121.918409,37.798152]}},{"type":"Feature","properties":{"stop_id":"2237","stop_code":"2237","stop_name":"Walnut Creek BART","location_type":0,"parent_station":"S5","agency_key":"county-connection","agency_name":"County Connection","routes":[{"route_id":"41","route_short_name":"ALCR","route_long_name":"Alamo Creek Shuttle","route_color":"46A076","route_text_color":"ffffff"}]},"geometry":{"type":"Point","coordinates":[-122.068615,37.905473]}}]}