{"type":"FeatureCollection","features":[{"type":"Feature","properties":{"stop_id":"700000001801","stop_name":"Europa Busway","routes":[{"route_id":"MET-95","agency_id":"MET","route_short_name":"95","route_long_name":"Royal Hospitals - City Centre","route_type":3},{"route_id":"MET-650","agency_id":"MET","route_short_name":"650","route_long_name":"Black's Road (Park + Ride) - Europa Buscentre","route_type":3},{"route_id":"MET-650A","agency_id":"MET","route_short_name":"650A","route_long_name":"Black's Road (Park + Ride) - Europa Buscentre","route_type":3}],"agency_name":"Translink"},"geometry":{"type":"Point","coordinates":[-5.94785,54.59163]}},{"type":"Feature","properties":{"stop_id":"700000015109","stop_name":"Black's Road P&R","routes":[{"route_id":"MET-650","agency_id":"MET","route_short_name":"650","route_long_name":"Black's Road (Park + Ride) - Europa Buscentre","route_type":3},{"route_id":"MET-650A","agency_id":"MET","route_short_name":"650A","route_long_name":"Black's Road (Park + Ride) - Europa Buscentre","route_type":3}],"agency_name":"Translink"},"geometry":{"type":"Point","coordinates":[-5.99454,54.55678]}},{"type":"Feature","properties":{"stop_id":"700000015363","stop_name":"Europa Buscentre","routes":[{"route_id":"MET-650","agency_id":"MET","route_short_name":"650","route_long_name":"Black's Road (Park + Ride) - Europa Buscentre","route_type":3},{"route_id":"MET-650A","agency_id":"MET","route_short_name":"650A","route_long_name":"Black's Road (Park + Ride) - Europa Buscentre","route_type":3}],"agency_name":"Translink"},"geometry":{"type":"Point","coordinates":[-5.93614,54.59449]}}]}